MANIFEST.in
setup.py
cleaver/__init__.py
cleaver/base.py
cleaver/experiment.py
cleaver/middleware.py
cleaver/util.py
cleaver.egg-info/PKG-INFO
cleaver.egg-info/SOURCES.txt
cleaver.egg-info/dependency_links.txt
cleaver.egg-info/not-zip-safe
cleaver.egg-info/top_level.txt
cleaver/backend/__init__.py
cleaver/backend/db/__init__.py
cleaver/backend/db/model.py
cleaver/backend/db/session.py
cleaver/compat/__init__.py
cleaver/compat/abc.py
cleaver/identity/__init__.py
cleaver/identity/beaker.py
cleaver/reports/__init__.py
cleaver/reports/web/__init__.py
cleaver/reports/web/bottle.py
cleaver/reports/web/views/index.tpl
cleaver/tests/__init__.py
cleaver/tests/test_base.py
cleaver/tests/test_experiment.py
cleaver/tests/test_middleware.py
cleaver/tests/test_stack.py
cleaver/tests/test_util.py
cleaver/tests/backend/__init__.py
cleaver/tests/backend/test_sqlalchemy.py
cleaver/tests/identity/__init__.py
cleaver/tests/identity/test_beaker.py
cleaver/tests/reports/__init__.py
cleaver/tests/reports/test_web.py